mkdocs_execute_plugin/__init__.py
mkdocs_execute_plugin/plugin.py
mkdocs_execute_plugin/utils.py
mkdocs_execute_plugin/tests/mkdocs.yml
mkdocs_execute_plugin/tests/test_mkdocs.py
mkdocs_execute_plugin/tests/docs/index.md
mkdocs_execute_plugin/tests/docs/jupytext.py
mkdocs_execute_plugin/tests/docs/python.py
mkdocs_execute_plugin/tests/docs/static.md
mkdocs_execute_plugin/tests/docs/nested/index.md
mkdocs_execute_plugin-0.0.9.dist-info/METADATA
mkdocs_execute_plugin-0.0.9.dist-info/WHEEL
mkdocs_execute_plugin-0.0.9.dist-info/entry_points.txt
mkdocs_execute_plugin-0.0.9.dist-info/licenses/AUTHORS.md
mkdocs_execute_plugin-0.0.9.dist-info/licenses/LICENSE
mkdocs_execute_plugin-0.0.9.dist-info/RECORD
