Metadata-Version: 2.4
Name: mkdocs-execute-plugin
Version: 0.0.9
Summary: A MkDocs plugin to execute notebooks and embed the results in the documentation.
Project-URL: Homepage, https://gitlab.kwant-project.org/qt/mkdocs-execute-plugin
Project-URL: Issues, https://gitlab.kwant-project.org/qt/mkdocs-execute-plugin/-/issues
Project-URL: Repository, https://gitlab.kwant-project.org/qt/mkdocs-execute-plugin.git
Author-email: MkDocs Execute Plugin Authors <mkdocs-execute-plugin@antonakhmerov.org>
License: BSD 2-Clause License
License-File: AUTHORS.md
License-File: LICENSE
Classifier: Framework :: MkDocs
Classifier: Operating System :: OS Independent
Requires-Python: >=3.8
Requires-Dist: ipykernel
Requires-Dist: jupytext
Requires-Dist: markdown
Requires-Dist: mkdocs>=1.4
Requires-Dist: nbconvert
Requires-Dist: traitlets
